pytoloka/__init__.py
pytoloka/exceptions.py
pytoloka/toloka.py
pytoloka/yandex.py
pytoloka-0.1.0.dist-info/LICENSE
pytoloka-0.1.0.dist-info/METADATA
pytoloka-0.1.0.dist-info/WHEEL
pytoloka-0.1.0.dist-info/top_level.txt
pytoloka-0.1.0.dist-info/RECORD
